certipy/__init__.py
certipy/__main__.py
certipy/certipy.py
certipy/command_line.py
certipy/version.py
certipy/test/__init__.py
certipy/test/test_certipy.py
certipy-0.2.1.dist-info/LICENSE
certipy-0.2.1.dist-info/METADATA
certipy-0.2.1.dist-info/NOTICE
certipy-0.2.1.dist-info/WHEEL
certipy-0.2.1.dist-info/entry_points.txt
certipy-0.2.1.dist-info/top_level.txt
certipy-0.2.1.dist-info/RECORD
