Metadata-Version: 2.1
Name: certipy
Version: 0.2.1
Summary: Utility to create and sign CAs and certificates
Author-email: Thomas Mendoza <mendoza33@llnl.gov>
License: BSD 3-Clause License
Project-URL: Homepage, https://github.com/LLNL/certipy
Keywords: pki,ssl,tls,certificates
Classifier: Development Status :: 4 - Beta
Classifier: Intended Audience :: Developers
Classifier: Topic :: Utilities
Classifier: License :: OSI Approved :: BSD License
Classifier: Programming Language :: Python :: 3
Classifier: Programming Language :: Python :: 3.7
Classifier: Programming Language :: Python :: 3.8
Classifier: Programming Language :: Python :: 3.9
Classifier: Programming Language :: Python :: 3.10
Classifier: Programming Language :: Python :: 3.11
Classifier: Programming Language :: Python :: 3.12
Requires-Python: >=3.7
License-File: LICENSE
License-File: NOTICE
Requires-Dist: cryptography
Provides-Extra: dev
Requires-Dist: pytest; extra == "dev"
Requires-Dist: flask; extra == "dev"
Requires-Dist: build; extra == "dev"
Requires-Dist: requests; extra == "dev"
Requires-Dist: pre-commit; extra == "dev"
Requires-Dist: ruff; extra == "dev"
Requires-Dist: bump-my-version; extra == "dev"
